mke/__init__.py
mke/analog.py
mke/digital.py
mke/pwm.py
mke/robot.py
mke_pypi_test-0.1.3.dist-info/LICENSE
mke_pypi_test-0.1.3.dist-info/METADATA
mke_pypi_test-0.1.3.dist-info/WHEEL
mke_pypi_test-0.1.3.dist-info/top_level.txt
mke_pypi_test-0.1.3.dist-info/RECORD
